<?xml version="1.0"?>
<detail><item><name>窦建平 副教授</name><wait1>职称副教授办公室机械楼533联系电话025-52090501-8533E-mailjp.dou@seu.edu.cn</wait1><wait4_kecheng>教授课程电工技术电子技术程序设计与算法语言II计算机综合课程设计现代控制理论</wait4_kecheng><wait_yanjiu>研究方向1.数字化制造与智能制造2.可重构制造系统与技术3.智能工业机器人系统与技术</wait_yanjiu><wait_huojiang>获奖情况1. 国防科技进步奖二等奖, 2011年</wait_huojiang><wait2_xuexi>学习经历1998年－2002年，南京航空航天大学，能源与动力学院，本科/工学学士2002年－2005年，南京航空航天大学，能源与动力学院，研究生/工学硕士2005年－2009年，东南大学，自动化学院，研究生/工学博士2016.9-2017.9，密歇根大学（安娜堡），机械工程系，访问学者</wait2_xuexi><wait3_gongzuo>工作经历2009年－2013，东南大学，机械工程学院，讲师2014年－至今，东南大学，机械工程学院，副教授</wait3_gongzuo></item></detail>
