<?xml version="1.0"?>
<detail><item><name>刘晓军</name><wait1>职称副教授办公室机械楼411联系电话18115604968E-mailliuxiaojun@seu.edu.cn</wait1><wait4_kecheng>教授课程程序设计与算法语言Ⅰ程序设计与算法语言Ⅱ计算机综合课程设计现代集成制造系统</wait4_kecheng><wait_yanjiu>研究方向1. 数字化设计与制造2. 先进制造技术</wait_yanjiu><wait_huojiang>获奖情况</wait_huojiang><wait2_xuexi>学习经历2001年－2005年，南京农业大学，工学院机械工程系，本科/学士2005年－2006年，东南大学，机械工程学院，研究生/直博2007年－2011年，东南大学，机械工程学院，研究生/博士</wait2_xuexi><wait3_gongzuo>工作经历2011年－2014年，东南大学，机械工程学院，讲师2014年－至今，东南大学，机械工程学院，副教授</wait3_gongzuo></item></detail>
